datasette_python.py
datasette_python-0.1.dist-info/LICENSE
datasette_python-0.1.dist-info/METADATA
datasette_python-0.1.dist-info/WHEEL
datasette_python-0.1.dist-info/entry_points.txt
datasette_python-0.1.dist-info/top_level.txt
datasette_python-0.1.dist-info/RECORD
