Metadata-Version: 2.1
Name: datasette-python
Version: 0.1
Summary: Run a Python interpreter in the Datasette virtual environment
Author: Simon Willison
License: Apache-2.0
Project-URL: Homepage, https://github.com/datasette/datasette-python
Project-URL: Changelog, https://github.com/datasette/datasette-python/releases
Project-URL: Issues, https://github.com/datasette/datasette-python/issues
Project-URL: CI, https://github.com/datasette/datasette-python/actions
Classifier: License :: OSI Approved :: Apache Software License
License-File: LICENSE
Requires-Dist: datasette
Provides-Extra: test
Requires-Dist: pytest ; extra == 'test'
